lxr_simple_notification_receiver/__init__.py
lxr_simple_notification_receiver/check_interpreter.py
lxr_simple_notification_receiver/check_package.py
lxr_simple_notification_receiver/logging_lib.py
lxr_simple_notification_receiver/simple_http_notification_conf.py
lxr_simple_notification_receiver/simple_http_notification_receiver.py
lxr_simple_notification_receiver/simple_http_notification_sender.py
lxr_simple_notification_receiver-0.1.3.dist-info/METADATA
lxr_simple_notification_receiver-0.1.3.dist-info/WHEEL
lxr_simple_notification_receiver-0.1.3.dist-info/top_level.txt
lxr_simple_notification_receiver-0.1.3.dist-info/RECORD
