Metadata-Version: 2.1
Name: lxr-simple-notification-receiver
Version: 0.1.3
Summary: A package for simplify my Python development, especially for Android development.
Home-page: https://github.com/hongwen000
Author: hongwen000
Author-email: hongwen000@outlook.com
Classifier: Development Status :: 3 - Alpha
Classifier: Intended Audience :: Developers
Classifier: License :: OSI Approved :: MIT License
Classifier: Programming Language :: Python :: 3
Classifier: Programming Language :: Python :: 3.7
Classifier: Programming Language :: Python :: 3.8
Classifier: Programming Language :: Python :: 3.9
Classifier: Programming Language :: Python :: 3.10
Classifier: Programming Language :: Python :: 3.11
